<?xml version="1.0"?>
<extension key="io.3sd.chainedsms" type="module">
  <file>chainedsms</file>
  <name>Chained SMS</name>
  <description>Create automated chains of outbound and inbound SMS.</description>
  <license>AGPL-3.0</license>
  <maintainer>
    <author>Michael McAndrew</author>
    <email>michaelmcandrew@thirdsectordesign.org</email>
  </maintainer>
  <releaseDate>2017-01-16</releaseDate>
  <version>1.0</version>
  <develStage>beta</develStage>
  <compatibility>
    <ver>4.6</ver>
    <ver>4.7</ver>
  </compatibility>
  <comments>Funding generously provided by Future First and National Democratic Institute.</comments>
  <civix>
    <namespace>CRM/ChainedSMS</namespace>
  </civix>
</extension>
